Metadata-Version: 1.0
Name: magpie-python
Version: 0.1
Summary: Magpie Python Library
Home-page: http://github.com/magpieim/magpie-python
Author: Jon Danao
Author-email: jon@magpie.im
License: MIT
Platform: UNKNOWN
